glycopeptidepy/algorithm.py
glycopeptidepy/enzyme.py
glycopeptidepy/version.py
glycopeptidepy/__init__.py
glycopeptidepy/test/__init__.py
glycopeptidepy/test/sequence_test_suite.py
glycopeptidepy/io/uniprot.py
glycopeptidepy/io/annotation.py
glycopeptidepy/io/nextprot.py
glycopeptidepy/io/mzid.py
glycopeptidepy/io/__init__.py
glycopeptidepy/io/utils.py
glycopeptidepy/io/fasta.py
glycopeptidepy/io/cv/peff.py
glycopeptidepy/io/cv/term.py
glycopeptidepy/io/cv/__init__.py
glycopeptidepy/io/cv/uniprot_ptm.py
glycopeptidepy/io/cv/data/__init__.py
glycopeptidepy/utils/memoize.py
glycopeptidepy/utils/collectiontools.py
glycopeptidepy/utils/sequence_tree.py
glycopeptidepy/utils/__init__.py
glycopeptidepy/utils/intervals.py
glycopeptidepy/utils/iterators.py
glycopeptidepy/_c/parser.pyx
glycopeptidepy/_c/compat.pxd
glycopeptidepy/_c/algorithm.cpython-311-darwin.so
glycopeptidepy/_c/count_table.cpython-311-darwin.so
glycopeptidepy/_c/collectiontools.c
glycopeptidepy/_c/parser.cpython-311-darwin.so
glycopeptidepy/_c/cythonize.py
glycopeptidepy/_c/algorithm.pyx
glycopeptidepy/_c/__init__.py
glycopeptidepy/_c/collectiontools.pxd
glycopeptidepy/_c/count_table.pxd
glycopeptidepy/_c/collectiontools.cpython-311-darwin.so
glycopeptidepy/_c/count_table.pyx
glycopeptidepy/_c/collectiontools.pyx
glycopeptidepy/_c/algorithm.c
glycopeptidepy/_c/compat.h
glycopeptidepy/_c/count_table.c
glycopeptidepy/_c/parser.c
glycopeptidepy/_c/parser.pxd
glycopeptidepy/_c/structure/sequence_methods.c
glycopeptidepy/_c/structure/fragment.c
glycopeptidepy/_c/structure/base.cpython-311-darwin.so
glycopeptidepy/_c/structure/constants.c
glycopeptidepy/_c/structure/sequence_methods.pxd
glycopeptidepy/_c/structure/glycan.pyx
glycopeptidepy/_c/structure/constants.pxd
glycopeptidepy/_c/structure/fragment.pxd
glycopeptidepy/_c/structure/base.c
glycopeptidepy/_c/structure/__init__.py
glycopeptidepy/_c/structure/base.pxd
glycopeptidepy-0.0.30.dist-info/RECORD
glycopeptidepy-0.0.30.dist-info/WHEEL
glycopeptidepy-0.0.30.dist-info/top_level.txt
glycopeptidepy-0.0.30.dist-info/METADATA
