Metadata-Version: 2.1
Name: glycopeptidepy
Version: 0.0.30
Requires-Dist: glypy>=1.0.13
Requires-Dist: six
Requires-Dist: lxml
Requires-Dist: rdflib
Requires-Dist: requests
Requires-Dist: SPARQLWrapper
